fastq_statistic/__init__.py
fastq_statistic/__main__.py
fastq_statistic/fastq_statistic
fastq_statistic/main.py
fastq_statistic-0.1.7.dist-info/entry_points.txt
fastq_statistic-0.1.7.dist-info/WHEEL
fastq_statistic-0.1.7.dist-info/METADATA
fastq_statistic-0.1.7.dist-info/RECORD
