Metadata-Version: 2.1
Name: fastq-statistic
Version: 0.1.7
Summary: 
Home-page: https://github.com/maoyibo/fastq_statistic
License: GPL-3.0-or-later
Author: Mao Yibo
Author-email: maoyibo@gmail.com
Requires-Python: >=3.8,<4.0
Classifier: License :: OSI Approved :: GNU General Public License v3 or later (GPLv3+)
Classifier: Operating System :: POSIX :: Linux
Classifier: Programming Language :: Python :: 3
Classifier: Programming Language :: Python :: 3.8
Classifier: Programming Language :: Python :: 3.9
Classifier: Topic :: Scientific/Engineering :: Bio-Informatics
Requires-Dist: matplotlib (>=3.3.3,<4.0.0)
Requires-Dist: numpy (>=1.19.5,<2.0.0)
Requires-Dist: pandas (>=1.2.1,<2.0.0)
Requires-Dist: typer (>=0.3.2,<0.4.0)
